pibooth_forget_button.py
pibooth_forget_button-1.0.0.dist-info/METADATA
pibooth_forget_button-1.0.0.dist-info/WHEEL
pibooth_forget_button-1.0.0.dist-info/entry_points.txt
pibooth_forget_button-1.0.0.dist-info/top_level.txt
pibooth_forget_button-1.0.0.dist-info/RECORD
