Metadata-Version: 2.4
Name: pibooth_forget_button
Version: 1.0.0
Summary: Pibooth plugin to add a third button for forgetting photos
Home-page: https://github.com/ceeeeb/pibooth-forget-button
Author: Ceeeeb
License: MIT license
Keywords: Raspberry Pi,photobooth,pibooth,button
Platform: unix
Platform: linux
Requires-Dist: pibooth>=2.0.0
Dynamic: author
Dynamic: description
Dynamic: home-page
Dynamic: keywords
Dynamic: license
Dynamic: platform
Dynamic: requires-dist
Dynamic: summary
